[
  {
    "id": 0,
    "state": 0,
    "prepTime": 5,
    "shipTime": 20,
    "totalTime": 25,
    "totalSum": 7.99,
    "boughtProducts": [
      {
        "id": 130,
        "category": "Food",
        "categoryId": 1,
        "name": "Cheeseburger",
        "price": 7.99,
        "prepTime": 5
      }
    ],
    "customer": {
      "email": "Fabian.Noll@gmail.com",
      "password": "Florian",
      "postal": "78532",
      "street": "Neuhauserstraße 71",
      "city": "Tuttlingen"
    }
  },
  {
    "id": 1,
    "state": 0,
    "prepTime": 5,
    "shipTime": 35,
    "totalTime": 40,
    "totalSum": 40.78,
    "boughtProducts": [
      {
        "id": 130,
        "category": "Food",
        "categoryId": 1,
        "name": "Cheeseburger",
        "price": 7.99,
        "prepTime": 5
      },
      {
        "onIce": true,
        "id": 223,
        "category": "Drink",
        "categoryId": 2,
        "name": "Coca Cola",
        "price": 2.99,
        "prepTime": 2
      },
      {
        "size": "L",
        "id": 273,
        "category": "Merchandise (Clothing)",
        "categoryId": 3,
        "name": "Hoodie",
        "price": 29.8,
        "prepTime": 0
      }
    ],
    "customer": {
      "email": "admin",
      "password": "admin",
      "postal": "admin",
      "street": "admin",
      "city": "admin"
    }
  }
]